<root>
  <docbasic>
    <doc_id></doc_id>
    <doc_symbol></doc_symbol>
  </docbasic>
  <usrbasic>
    <usr_name></usr_name>
    <usr_nickname></usr_nickname>
    <coins></coins>
	<sex></sex>
	<birthday></birthday>
	<state></state>
	<city></city>
	<school></school>
    <account_status></account_status>
    <account_limited></account_limited>
    <account_head></account_head>
    <account_childs></account_childs>
    <account_sms></account_sms>
  </usrbasic>
  <valueadded>
	<personalstore>
		<isallowed>1</isallowed>
		<storesymbol></storesymbol>
		<maxitem>100</maxitem>		
	</personalstore>
  </valueadded>
  <studystatus>
    <fiststarttime></fiststarttime>
    <currentsence>
	  <symbol></symbol>
      <currentstage></currentstage>
    </currentsence>    
  </studystatus>
  <lessons>    
    <begin></begin>
    <intermediate></intermediate>
    <senior></senior>
  </lessons>
  <friends></friends>
  <codetime></codetime>
</root>